packaging/__about__.py
packaging/__init__.py
packaging/_manylinux.py
packaging/_musllinux.py
packaging/_structures.py
packaging/markers.py
packaging/py.typed
packaging/requirements.py
packaging/specifiers.py
packaging/tags.py
packaging/utils.py
packaging/version.py
packaging-21.1.dist-info/LICENSE
packaging-21.1.dist-info/LICENSE.APACHE
packaging-21.1.dist-info/LICENSE.BSD
packaging-21.1.dist-info/METADATA
packaging-21.1.dist-info/WHEEL
packaging-21.1.dist-info/top_level.txt
packaging-21.1.dist-info/RECORD
