Metadata-Version: 2.1
Name: packaging
Version: 21.1
Summary: Core utilities for Python packages
Home-page: https://github.com/pypa/packaging
Author: Donald Stufft and individual contributors
Author-email: donald@stufft.io
License: BSD-2-Clause or Apache-2.0
Platform: UNKNOWN
Classifier: Development Status :: 5 - Production/Stable
Classifier: Intended Audience :: Developers
Classifier: License :: OSI Approved :: Apache Software License
Classifier: License :: OSI Approved :: BSD License
Classifier: Programming Language :: Python
Classifier: Programming Language :: Python :: 3
Classifier: Programming Language :: Python :: 3 :: Only
Classifier: Programming Language :: Python :: 3.6
Classifier: Programming Language :: Python :: 3.7
Classifier: Programming Language :: Python :: 3.8
Classifier: Programming Language :: Python :: 3.9
Classifier: Programming Language :: Python :: 3.10
Classifier: Programming Language :: Python :: Implementation :: CPython
Classifier: Programming Language :: Python :: Implementation :: PyPy
Requires-Python: >=3.6
License-File: LICENSE
License-File: LICENSE.APACHE
License-File: LICENSE.BSD
Requires-Dist: pyparsing (<3,>=2.0.2)
